{
  "asset": {
    "generatetool": "cesiumlab2@www.cesiumlab.com/model2tiles",
    "version": "1.0"
  },
  "extras": {
    "scenetree": "scenetree.json"
  },
  "geometricError": 1009.32368442696,
  "properties": null,
  "refine": "REPLACE",
  "root": {
    "boundingVolume": {
      "box": [
        6.98491930961609e-10,
        0.0118709316011518,
        16.0000005639158,
        504.661842213478,
        0,
        0,
        0,
        343.591750000836,
        0,
        0,
        0,
        15.0000004009344
      ]
    },
    "children": [
      {
        "boundingVolume": {
          "box": [
            0.00362347415648401,
            0.00671292445622385,
            16.0183503394946,
            504.646976310061,
            0,
            0,
            0,
            343.591108802939,
            0,
            0,
            0,
            15.0107079045847
          ]
        },
        "content": {
          "uri": "NoLod_0.b3dm"
        },
        "geometricError": 0.0,
        "refine": "REPLACE"
      }
    ],
    "geometricError": 1009.32368442696,
    "transform": [
      -0.970353951149448,
      -0.24168824855308,
      0.0,
      0.0,
      0.122972062180094,
      -0.493720431720715,
      0.860882109945773,
      0.0,
      -0.208065089363474,
      0.835360356859754,
      0.508804474012674,
      0.0,
      -1328218.86743239,
      5332664.84291316,
      3226296.23974825,
      1.0
    ]
  }
}